CHANGES.rst
LICENSE
MANIFEST.in
README.rst
setup.py
txwatcher.py
txwatcher.egg-info/PKG-INFO
txwatcher.egg-info/SOURCES.txt
txwatcher.egg-info/dependency_links.txt
txwatcher.egg-info/requires.txt
txwatcher.egg-info/top_level.txt